mofdscribe/__init__.py
mofdscribe/constants.py
mofdscribe/helpers.py
mofdscribe/types.py
mofdscribe/version.py
mofdscribe/bench/__init__.py
mofdscribe/bench/bandgap.py
mofdscribe/bench/ch4dc.py
mofdscribe/bench/df_model.py
mofdscribe/bench/dummy_models.py
mofdscribe/bench/logkHCO2.py
mofdscribe/bench/mofbench.py
mofdscribe/bench/pbegap.py
mofdscribe/bench/watermark.py
mofdscribe/datasets/__init__.py
mofdscribe/datasets/arabg_dataset.py
mofdscribe/datasets/arcmof_dataset.py
mofdscribe/datasets/bw_dataset.py
mofdscribe/datasets/checks.py
mofdscribe/datasets/core_dataset.py
mofdscribe/datasets/dataset.py
mofdscribe/datasets/qmof_dataset.py
mofdscribe/datasets/structuredataset.py
mofdscribe/datasets/thermal_stability_dataset.py
mofdscribe/datasets/utils.py
mofdscribe/featurizers/__init__.py
mofdscribe/featurizers/base.py
mofdscribe/featurizers/bu/__init__.py
mofdscribe/featurizers/bu/bu_featurizer.py
mofdscribe/featurizers/bu/bu_matches.py
mofdscribe/featurizers/bu/compositionstats_featurizer.py
mofdscribe/featurizers/bu/distance_hist_featurizer.py
mofdscribe/featurizers/bu/distance_stats_featurizer.py
mofdscribe/featurizers/bu/lsop_featurizer.py
mofdscribe/featurizers/bu/nconf20_featurizer.py
mofdscribe/featurizers/bu/prototype_env.json
mofdscribe/featurizers/bu/rdkitadaptor.py
mofdscribe/featurizers/bu/shape_featurizer.py
mofdscribe/featurizers/bu/smarts_matches.py
mofdscribe/featurizers/bu/utils.py
mofdscribe/featurizers/chemistry/__init__.py
mofdscribe/featurizers/chemistry/_fragment.py
mofdscribe/featurizers/chemistry/amd.py
mofdscribe/featurizers/chemistry/aprdf.py
mofdscribe/featurizers/chemistry/energygrid.py
mofdscribe/featurizers/chemistry/henry.py
mofdscribe/featurizers/chemistry/partialchargehistogram.py
mofdscribe/featurizers/chemistry/partialchargestats.py
mofdscribe/featurizers/chemistry/price.py
mofdscribe/featurizers/chemistry/racs.py
mofdscribe/featurizers/chemistry/data/elementprices.csv
mofdscribe/featurizers/hostguest/__init__.py
mofdscribe-0.0.8.dist-info/LICENSE
mofdscribe-0.0.8.dist-info/METADATA
mofdscribe-0.0.8.dist-info/WHEEL
mofdscribe-0.0.8.dist-info/top_level.txt
mofdscribe-0.0.8.dist-info/RECORD
