Metadata-Version: 2.1
Name: mofdscribe
Version: 0.0.8
Summary: Ecosystem for digital reticular chemistry
Home-page: https://github.com/kjappelbaum/mofdscribe
Download-URL: https://github.com/kjappelbaum/mofdscribe/releases
Author: Kevin M. Jablonka
Author-email: mail@kjablonka.com
Maintainer: Kevin M. Jablonka
Maintainer-email: mail@kjablonka.com
License: MIT
Project-URL: Bug Tracker, https://github.com/kjappelbaum/mofdscribe/issues
Project-URL: Source Code, https://github.com/kjappelbaum/mofdscribe
Keywords: mof,machine-learning,descriptors,featurization,reticular-chemistry
Classifier: Development Status :: 1 - Planning
Classifier: Environment :: Console
Classifier: Intended Audience :: Developers
Classifier: License :: OSI Approved :: MIT License
Classifier: Operating System :: OS Independent
Classifier: Framework :: Pytest
Classifier: Framework :: tox
Classifier: Framework :: Sphinx
Classifier: Programming Language :: Python
Classifier: Programming Language :: Python :: 3.8
Classifier: Programming Language :: Python :: 3.9
Classifier: Programming Language :: Python :: 3.10
Classifier: Programming Language :: Python :: 3 :: Only
Requires-Python: >=3.8
License-File: LICENSE
Requires-Dist: numpy
Requires-Dist: matminer
Requires-Dist: loguru
Requires-Dist: pystow
Requires-Dist: ase
Requires-Dist: structuregraph-helpers
Requires-Dist: element-coder
Requires-Dist: pydantic
Requires-Dist: typing-extensions
Provides-Extra: all
Requires-Dist: pervect ; extra == 'all'
Requires-Dist: average-minimum-distance ; extra == 'all'
Requires-Dist: superpose3d ; extra == 'all'
Requires-Dist: rdkit ; extra == 'all'
Requires-Dist: moffragmentor ; extra == 'all'
Requires-Dist: moleculetda ; extra == 'all'
Requires-Dist: pyeqeq ; extra == 'all'
Requires-Dist: nglview ; extra == 'all'
Provides-Extra: amd
Requires-Dist: average-minimum-distance ; extra == 'amd'
Provides-Extra: bbmatch
Requires-Dist: superpose3d ; extra == 'bbmatch'
Provides-Extra: buildchart
Requires-Dist: holoviews ; extra == 'buildchart'
Requires-Dist: bokeh ; extra == 'buildchart'
Provides-Extra: docs
Requires-Dist: sphinx ; extra == 'docs'
Requires-Dist: furo ; extra == 'docs'
Requires-Dist: sphinx-click ; extra == 'docs'
Requires-Dist: sphinx-autodoc-typehints ; extra == 'docs'
Requires-Dist: sphinx-automodapi ; extra == 'docs'
Requires-Dist: sphinx-copybutton ; extra == 'docs'
Requires-Dist: sphinxcontrib-katex ; extra == 'docs'
Requires-Dist: sphinxcontrib-needs ; extra == 'docs'
Requires-Dist: sphinxcontrib-plantuml ; extra == 'docs'
Requires-Dist: sphinx-pydantic ; extra == 'docs'
Requires-Dist: sphinx-jsonschema (<=1.15) ; extra == 'docs'
Provides-Extra: eqeq
Requires-Dist: pyeqeq ; extra == 'eqeq'
Provides-Extra: lint
Requires-Dist: isort (<5) ; extra == 'lint'
Requires-Dist: black ; extra == 'lint'
Requires-Dist: flake8 (<5) ; extra == 'lint'
Requires-Dist: pre-commit ; extra == 'lint'
Requires-Dist: bumpversion ; extra == 'lint'
Provides-Extra: pervect
Requires-Dist: pervect ; extra == 'pervect'
Provides-Extra: sbu
Requires-Dist: rdkit ; extra == 'sbu'
Requires-Dist: moffragmentor ; extra == 'sbu'
Provides-Extra: tda
Requires-Dist: moleculetda ; extra == 'tda'
Provides-Extra: tests
Requires-Dist: pytest ; extra == 'tests'
Requires-Dist: tox ; extra == 'tests'
Requires-Dist: coverage ; extra == 'tests'
Requires-Dist: dscribe ; extra == 'tests'
Requires-Dist: pytest-xdist ; extra == 'tests'
Provides-Extra: visualization
Requires-Dist: nglview ; extra == 'visualization'
